erfc/__init__.py
erfc/get.py
erfc/tests/__init__.py
erfc/tests/test_get.py
erfc-0.1.0.dist-info/LICENSE
erfc-0.1.0.dist-info/METADATA
erfc-0.1.0.dist-info/WHEEL
erfc-0.1.0.dist-info/entry_points.txt
erfc-0.1.0.dist-info/top_level.txt
erfc-0.1.0.dist-info/RECORD
